small_web_dataset/__init__.py
small_web_dataset/_modidx.py
small_web_dataset/feeds.py
small_web_dataset/language_detection.py
small_web_dataset/main.py
small_web_dataset-0.0.2.dist-info/LICENSE
small_web_dataset-0.0.2.dist-info/METADATA
small_web_dataset-0.0.2.dist-info/WHEEL
small_web_dataset-0.0.2.dist-info/entry_points.txt
small_web_dataset-0.0.2.dist-info/top_level.txt
small_web_dataset-0.0.2.dist-info/RECORD
