Metadata-Version: 2.1
Name: small-web-dataset
Version: 0.0.2
Summary: Process all the RSS and Atom feeds from the Small Web feeds list, validate them, generate statistics and eventually more.
Home-page: https://github.com/fgiasson/small-web-dataset
Author: Frederick Giasson
Author-email: Frederick Giasson <fred@fgiasson.com>
License: GNU GPLv3
Project-URL: Homepage, https://github.com/fgiasson/small-web-dataset
Project-URL: Bug Tracker, https://github.com/fgiasson/small-web-dataset/issues
Keywords: nbdev jupyter notebook python
Classifier: Programming Language :: Python :: 3
Classifier: Operating System :: OS Independent
Requires-Python: >=3.10
License-File: LICENSE
Requires-Dist: typer[all]
Requires-Dist: python-dotenv
Requires-Dist: requests
Requires-Dist: feedparser ==6.0.10
Requires-Dist: transformers
Requires-Dist: torch
Requires-Dist: langdetect
Provides-Extra: dev
